rg_python_utils/__init__.py
rg_python_utils/base_model.py
rg_python_utils/base_request.py
rg_python_utils/caching.py
rg_python_utils/database_util.py
rg_python_utils/rg_cipher.py
rg_python_utils/rg_compression.py
rg_python_utils/rg_enum_base.py
rg_python_utils/rg_exceptions.py
rg_python_utils/rg_logger.py
rg_python_utils/rg_logger_cache.py
rg_python_utils/rg_utils.py
rg_python_utils/urls.py
rg_python_utils/views.py
rg_python_utils/rg_redis/__init__.py
rg_python_utils/rg_redis/cache.py
rg_python_utils/rg_redis/exceptions.py
rg_python_utils/rg_redis/redis_cache.py
rg_python_utils/rg_redis/redis_manager.py
rg_python_utils/zlib/__init__.py
rg_python_utils/zlib/zlib.py
rg_python_utils-0.0.22.dist-info/METADATA
rg_python_utils-0.0.22.dist-info/WHEEL
rg_python_utils-0.0.22.dist-info/top_level.txt
rg_python_utils-0.0.22.dist-info/RECORD
