Metadata-Version: 2.1
Name: rg-python-utils
Version: 0.0.22
Summary: rg python util package
Home-page: https://github.com/shail-rgames/rg_python_utils
Author: Shailendra Sharma
Author-email: shail.rgames@gmail.com
License: UNKNOWN
Platform: UNKNOWN
Classifier: Programming Language :: Python :: 3.7
Classifier: License :: OSI Approved :: MIT License
Classifier: Operating System :: OS Independent
